pytorch_pip_shim/__init__.py
pytorch_pip_shim/__main__.py
pytorch_pip_shim/_version.py
pytorch_pip_shim/computation_backend.py
pytorch_pip_shim/patch.py
pytorch_pip_shim/py.typed
pytorch_pip_shim/shim.py
pytorch_pip_shim/utils.py
pytorch_pip_shim/cli/__init__.py
pytorch_pip_shim/cli/commands.py
pytorch_pip_shim-0.1.0.dist-info/LICENSE
pytorch_pip_shim-0.1.0.dist-info/METADATA
pytorch_pip_shim-0.1.0.dist-info/WHEEL
pytorch_pip_shim-0.1.0.dist-info/entry_points.txt
pytorch_pip_shim-0.1.0.dist-info/top_level.txt
pytorch_pip_shim-0.1.0.dist-info/RECORD
