Metadata-Version: 2.1
Name: pytorch-pip-shim
Version: 0.1.0
Summary: Patch pip to play ball with PyTorch
Home-page: https://github.com/pmeier/pytorch-pip-shim
Author: Philip Meier
Author-email: github.pmeier@posteo.de
License: BSD-3-Clause
Project-URL: Source, https://github.com/pmeier/pytorch-pip-shim
Project-URL: Tracker, https://github.com/pmeier/pytorch-pip-shim/issues
Keywords: pytorch,installation,pip,shim,patch,utility
Platform: any
Classifier: Development Status :: 3 - Alpha
Classifier: License :: OSI Approved :: BSD License
Classifier: Programming Language :: Python :: 3.6
Classifier: Programming Language :: Python :: 3.7
Classifier: Programming Language :: Python :: 3.8
Classifier: Typing :: Typed
Requires-Python: >=3.6
Requires-Dist: pip (>=20.2)
